atopos/LICENSE
atopos/__init__.py
atopos/_data/__init__.py
atopos/_data/h38_gene_info_v43.csv.gz
atopos/_data/m39_gene_info_v32.csv.gz
atopos/ml/__init__.py
atopos/ml/_ml.py
atopos/pl/__init__.py
atopos/pl/_palette.py
atopos/pl/forest.py
atopos/st/__init__.py
atopos/st/_stringpy.py
atopos/tl/_IO.py
atopos/tl/__init__.py
atopos/tl/_frame.py
atopos/tl/gene.py
atopos/tl/utils.py
atopos-1.0.0.dist-info/METADATA
atopos-1.0.0.dist-info/WHEEL
atopos-1.0.0.dist-info/RECORD
