Metadata-Version: 2.4
Name: atopos
Version: 1.0.0
Summary: Bioinformatics data analysis and visualization toolkit
Project-URL: Homepage, https://github.com/ScienceAdvances/atopos
Author-email: 生信探索 BioQuest <yehior@qq.com>
Classifier: Development Status :: 4 - Beta
Classifier: Intended Audience :: Developers
Classifier: Operating System :: OS Independent
Classifier: Programming Language :: Python :: 3
Classifier: Programming Language :: Python :: 3.10
Requires-Python: >=3.9
Requires-Dist: bioinfokit>2
Requires-Dist: joblib>1.2.0
Requires-Dist: matplotlib-venn>0.11
Requires-Dist: matplotlib>3
Requires-Dist: numpy>1.19.5
Requires-Dist: pandas>1.5
Requires-Dist: scikit-learn>1.0
Requires-Dist: scipy>1.6.0
Requires-Dist: seaborn>0.10
Requires-Dist: threadpoolctl>3.1.0
